setup.py
Django_base.egg-info/PKG-INFO
Django_base.egg-info/SOURCES.txt
Django_base.egg-info/dependency_links.txt
Django_base.egg-info/not-zip-safe
Django_base.egg-info/requires.txt
Django_base.egg-info/top_level.txt
djangobase/__init__.py
djangobase/generator.py
djangobase/bin/mkdjango