Metadata-Version: 1.0
Name: Django-base
Version: v1.1
Summary: Django-base project setup
Home-page: https://github.com/macmichael01/django-base
Author: Chris McMichael
Author-email: macmichael01@gmail.com
License: BSD
Keywords: django python setup
Platform: UNKNOWN
